pycolorz/__init__.py
pycolorz/color.py
pycolorz-0.0.9.dist-info/METADATA
pycolorz-0.0.9.dist-info/WHEEL
pycolorz-0.0.9.dist-info/top_level.txt
pycolorz-0.0.9.dist-info/RECORD
