Metadata-Version: 2.1
Name: pycolorz
Version: 0.0.9
Summary: A Python Library
Author: Themonkey094
